devbricksx/__init__.py
devbricksx/apm/__init__.py
devbricksx/apm/exec_time.py
devbricksx/async/__init__.py
devbricksx/async/managed_thread.py
devbricksx/development/__init__.py
devbricksx/development/log.py
devbricksx/image/__init__.py
devbricksx/image/image_utils.py
devbricksx/text/__init__.py
devbricksx/text/text_utils.py
devbricksx_py-0.1.0.dist-info/LICENSE
devbricksx_py-0.1.0.dist-info/METADATA
devbricksx_py-0.1.0.dist-info/WHEEL
devbricksx_py-0.1.0.dist-info/top_level.txt
devbricksx_py-0.1.0.dist-info/RECORD
