Metadata-Version: 2.1
Name: devbricksx-py
Version: 0.1.0
Summary: DevBricks X Python  provides several classes which will usually be used in everyday Python development
Home-page: https://github.com/dailystudio/devbricksx-py
Author: Daily Studio
Author-email: dailystudio2010@gmail.com
License: Apache License 2.0
Classifier: Programming Language :: Python :: 3
Classifier: License :: OSI Approved :: Apache Software License
Classifier: Operating System :: OS Independent
Requires-Python: >=3.6
License-File: LICENSE
Requires-Dist: Pillow>=10.2.0
Requires-Dist: numpy
